karavaisv/__init__.py
karavaisv/main.py
karavaisv/parsing_args.py
karavaisv/rendering.py
karavaisv/util_funcs.py
karavaisv-0.1.0.dist-info/licenses/LICENSE
karavaisv-0.1.0.dist-info/METADATA
karavaisv-0.1.0.dist-info/WHEEL
karavaisv-0.1.0.dist-info/entry_points.txt
karavaisv-0.1.0.dist-info/top_level.txt
karavaisv-0.1.0.dist-info/RECORD
