Metadata-Version: 2.4
Name: karavaisv
Version: 0.1.0
Summary: Powerful yet simple-to-use templating tool for SystemVerilog with plenty of useful features.
Author-email: Denis Panin <lozejor12@gmail.com>
License-Expression: MIT
Project-URL: Homepage, https://github.com/BIG-Denis/karavaisv
Project-URL: Issues, https://github.com/BIG-Denis/karavaisv/issues
Classifier: Programming Language :: Python :: 3
Requires-Python: >=3.10
License-File: LICENSE
Requires-Dist: pyyaml
Dynamic: license-file
